{
  "version": "0.3.14-fixed",
  "steps": [
    {
      "stepType": "CreateEnum",
      "enum": "Role",
      "values": [
        "CUSTOMER",
        "ADMIN"
      ]
    },
    {
      "stepType": "CreateEnum",
      "enum": "TestSessionState",
      "values": [
        "PENDING",
        "UNRESOLVED",
        "ACCEPTED",
        "DECLINED"
      ]
    },
    {
      "stepType": "CreateModel",
      "model": "User"
    },
    {
      "stepType": "CreateField",
      "model": "User",
      "field": "id",
      "type": "String",
      "arity": "required"
    },
    {
      "stepType": "CreateDirective",
      "model": "User",
      "field": "id",
      "directive": "id"
    },
    {
      "stepType": "CreateDirective",
      "model": "User",
      "field": "id",
      "directive": "default"
    },
    {
      "stepType": "CreateDirectiveArgument",
      "model": "User",
      "field": "id",
      "directive": "default",
      "argument": "",
      "value": "cuid()"
    },
    {
      "stepType": "CreateField",
      "model": "User",
      "field": "createdAt",
      "type": "DateTime",
      "arity": "required"
    },
    {
      "stepType": "CreateDirective",
      "model": "User",
      "field": "createdAt",
      "directive": "default"
    },
    {
      "stepType": "CreateDirectiveArgument",
      "model": "User",
      "field": "createdAt",
      "directive": "default",
      "argument": "",
      "value": "now()"
    },
    {
      "stepType": "CreateField",
      "model": "User",
      "field": "updatedAt",
      "type": "DateTime",
      "arity": "required"
    },
    {
      "stepType": "CreateDirective",
      "model": "User",
      "field": "updatedAt",
      "directive": "updatedAt"
    },
    {
      "stepType": "CreateField",
      "model": "User",
      "field": "email",
      "type": "String",
      "arity": "required"
    },
    {
      "stepType": "CreateDirective",
      "model": "User",
      "field": "email",
      "directive": "unique"
    },
    {
      "stepType": "CreateField",
      "model": "User",
      "field": "password",
      "type": "String",
      "arity": "required"
    },
    {
      "stepType": "CreateField",
      "model": "User",
      "field": "lastname",
      "type": "String",
      "arity": "optional"
    },
    {
      "stepType": "CreateField",
      "model": "User",
      "field": "forename",
      "type": "String",
      "arity": "optional"
    },
    {
      "stepType": "CreateField",
      "model": "User",
      "field": "active",
      "type": "Boolean",
      "arity": "required"
    },
    {
      "stepType": "CreateDirective",
      "model": "User",
      "field": "active",
      "directive": "default"
    },
    {
      "stepType": "CreateDirectiveArgument",
      "model": "User",
      "field": "active",
      "directive": "default",
      "argument": "",
      "value": "false"
    },
    {
      "stepType": "CreateField",
      "model": "User",
      "field": "role",
      "type": "Role",
      "arity": "required"
    },
    {
      "stepType": "CreateDirective",
      "model": "User",
      "field": "role",
      "directive": "default"
    },
    {
      "stepType": "CreateDirectiveArgument",
      "model": "User",
      "field": "role",
      "directive": "default",
      "argument": "",
      "value": "CUSTOMER"
    },
    {
      "stepType": "CreateField",
      "model": "User",
      "field": "apiKey",
      "type": "String",
      "arity": "required"
    },
    {
      "stepType": "CreateDirective",
      "model": "User",
      "field": "apiKey",
      "directive": "unique"
    },
    {
      "stepType": "CreateModel",
      "model": "Project"
    },
    {
      "stepType": "CreateField",
      "model": "Project",
      "field": "id",
      "type": "String",
      "arity": "required"
    },
    {
      "stepType": "CreateDirective",
      "model": "Project",
      "field": "id",
      "directive": "id"
    },
    {
      "stepType": "CreateDirective",
      "model": "Project",
      "field": "id",
      "directive": "default"
    },
    {
      "stepType": "CreateDirectiveArgument",
      "model": "Project",
      "field": "id",
      "directive": "default",
      "argument": "",
      "value": "cuid()"
    },
    {
      "stepType": "CreateField",
      "model": "Project",
      "field": "createdAt",
      "type": "DateTime",
      "arity": "required"
    },
    {
      "stepType": "CreateDirective",
      "model": "Project",
      "field": "createdAt",
      "directive": "default"
    },
    {
      "stepType": "CreateDirectiveArgument",
      "model": "Project",
      "field": "createdAt",
      "directive": "default",
      "argument": "",
      "value": "now()"
    },
    {
      "stepType": "CreateField",
      "model": "Project",
      "field": "updatedAt",
      "type": "DateTime",
      "arity": "required"
    },
    {
      "stepType": "CreateDirective",
      "model": "Project",
      "field": "updatedAt",
      "directive": "updatedAt"
    },
    {
      "stepType": "CreateField",
      "model": "Project",
      "field": "name",
      "type": "String",
      "arity": "required"
    },
    {
      "stepType": "CreateField",
      "model": "Project",
      "field": "description",
      "type": "String",
      "arity": "optional"
    },
    {
      "stepType": "CreateField",
      "model": "Project",
      "field": "tests",
      "type": "Test",
      "arity": "list"
    },
    {
      "stepType": "CreateModel",
      "model": "Test"
    },
    {
      "stepType": "CreateField",
      "model": "Test",
      "field": "id",
      "type": "String",
      "arity": "required"
    },
    {
      "stepType": "CreateDirective",
      "model": "Test",
      "field": "id",
      "directive": "id"
    },
    {
      "stepType": "CreateDirective",
      "model": "Test",
      "field": "id",
      "directive": "default"
    },
    {
      "stepType": "CreateDirectiveArgument",
      "model": "Test",
      "field": "id",
      "directive": "default",
      "argument": "",
      "value": "cuid()"
    },
    {
      "stepType": "CreateField",
      "model": "Test",
      "field": "createdAt",
      "type": "DateTime",
      "arity": "required"
    },
    {
      "stepType": "CreateDirective",
      "model": "Test",
      "field": "createdAt",
      "directive": "default"
    },
    {
      "stepType": "CreateDirectiveArgument",
      "model": "Test",
      "field": "createdAt",
      "directive": "default",
      "argument": "",
      "value": "now()"
    },
    {
      "stepType": "CreateField",
      "model": "Test",
      "field": "updatedAt",
      "type": "DateTime",
      "arity": "required"
    },
    {
      "stepType": "CreateDirective",
      "model": "Test",
      "field": "updatedAt",
      "directive": "updatedAt"
    },
    {
      "stepType": "CreateField",
      "model": "Test",
      "field": "name",
      "type": "String",
      "arity": "required"
    },
    {
      "stepType": "CreateField",
      "model": "Test",
      "field": "project",
      "type": "Project",
      "arity": "required"
    },
    {
      "stepType": "CreateField",
      "model": "Test",
      "field": "variations",
      "type": "Variation",
      "arity": "list"
    },
    {
      "stepType": "CreateModel",
      "model": "Variation"
    },
    {
      "stepType": "CreateField",
      "model": "Variation",
      "field": "id",
      "type": "String",
      "arity": "required"
    },
    {
      "stepType": "CreateDirective",
      "model": "Variation",
      "field": "id",
      "directive": "id"
    },
    {
      "stepType": "CreateDirective",
      "model": "Variation",
      "field": "id",
      "directive": "default"
    },
    {
      "stepType": "CreateDirectiveArgument",
      "model": "Variation",
      "field": "id",
      "directive": "default",
      "argument": "",
      "value": "cuid()"
    },
    {
      "stepType": "CreateField",
      "model": "Variation",
      "field": "createdAt",
      "type": "DateTime",
      "arity": "required"
    },
    {
      "stepType": "CreateDirective",
      "model": "Variation",
      "field": "createdAt",
      "directive": "default"
    },
    {
      "stepType": "CreateDirectiveArgument",
      "model": "Variation",
      "field": "createdAt",
      "directive": "default",
      "argument": "",
      "value": "now()"
    },
    {
      "stepType": "CreateField",
      "model": "Variation",
      "field": "updatedAt",
      "type": "DateTime",
      "arity": "required"
    },
    {
      "stepType": "CreateDirective",
      "model": "Variation",
      "field": "updatedAt",
      "directive": "updatedAt"
    },
    {
      "stepType": "CreateField",
      "model": "Variation",
      "field": "browserName",
      "type": "String",
      "arity": "required"
    },
    {
      "stepType": "CreateField",
      "model": "Variation",
      "field": "deviceName",
      "type": "String",
      "arity": "required"
    },
    {
      "stepType": "CreateField",
      "model": "Variation",
      "field": "test",
      "type": "Test",
      "arity": "required"
    },
    {
      "stepType": "CreateField",
      "model": "Variation",
      "field": "testSessions",
      "type": "TestSession",
      "arity": "list"
    },
    {
      "stepType": "CreateField",
      "model": "Variation",
      "field": "additionalData",
      "type": "String",
      "arity": "optional"
    },
    {
      "stepType": "CreateField",
      "model": "Variation",
      "field": "baseline",
      "type": "TestSession",
      "arity": "optional"
    },
    {
      "stepType": "CreateDirective",
      "model": "Variation",
      "field": "baseline",
      "directive": "relation"
    },
    {
      "stepType": "CreateDirectiveArgument",
      "model": "Variation",
      "field": "baseline",
      "directive": "relation",
      "argument": "name",
      "value": "\"VariationBaseline\""
    },
    {
      "stepType": "CreateModel",
      "model": "TestSession"
    },
    {
      "stepType": "CreateField",
      "model": "TestSession",
      "field": "id",
      "type": "String",
      "arity": "required"
    },
    {
      "stepType": "CreateDirective",
      "model": "TestSession",
      "field": "id",
      "directive": "id"
    },
    {
      "stepType": "CreateDirective",
      "model": "TestSession",
      "field": "id",
      "directive": "default"
    },
    {
      "stepType": "CreateDirectiveArgument",
      "model": "TestSession",
      "field": "id",
      "directive": "default",
      "argument": "",
      "value": "cuid()"
    },
    {
      "stepType": "CreateField",
      "model": "TestSession",
      "field": "createdAt",
      "type": "DateTime",
      "arity": "required"
    },
    {
      "stepType": "CreateDirective",
      "model": "TestSession",
      "field": "createdAt",
      "directive": "default"
    },
    {
      "stepType": "CreateDirectiveArgument",
      "model": "TestSession",
      "field": "createdAt",
      "directive": "default",
      "argument": "",
      "value": "now()"
    },
    {
      "stepType": "CreateField",
      "model": "TestSession",
      "field": "updatedAt",
      "type": "DateTime",
      "arity": "required"
    },
    {
      "stepType": "CreateDirective",
      "model": "TestSession",
      "field": "updatedAt",
      "directive": "updatedAt"
    },
    {
      "stepType": "CreateField",
      "model": "TestSession",
      "field": "diffImageKey",
      "type": "String",
      "arity": "optional"
    },
    {
      "stepType": "CreateField",
      "model": "TestSession",
      "field": "imageKey",
      "type": "String",
      "arity": "optional"
    },
    {
      "stepType": "CreateField",
      "model": "TestSession",
      "field": "misMatchPercentage",
      "type": "Float",
      "arity": "optional"
    },
    {
      "stepType": "CreateField",
      "model": "TestSession",
      "field": "misMatchTolerance",
      "type": "Float",
      "arity": "required"
    },
    {
      "stepType": "CreateField",
      "model": "TestSession",
      "field": "isSameDimensions",
      "type": "Boolean",
      "arity": "optional"
    },
    {
      "stepType": "CreateField",
      "model": "TestSession",
      "field": "variation",
      "type": "Variation",
      "arity": "required"
    },
    {
      "stepType": "CreateField",
      "model": "TestSession",
      "field": "state",
      "type": "TestSessionState",
      "arity": "required"
    },
    {
      "stepType": "CreateDirective",
      "model": "TestSession",
      "field": "state",
      "directive": "default"
    },
    {
      "stepType": "CreateDirectiveArgument",
      "model": "TestSession",
      "field": "state",
      "directive": "default",
      "argument": "",
      "value": "PENDING"
    },
    {
      "stepType": "CreateField",
      "model": "TestSession",
      "field": "stateChangedByUser",
      "type": "User",
      "arity": "optional"
    },
    {
      "stepType": "CreateField",
      "model": "TestSession",
      "field": "stateComment",
      "type": "String",
      "arity": "optional"
    },
    {
      "stepType": "CreateField",
      "model": "TestSession",
      "field": "autoBaseline",
      "type": "Boolean",
      "arity": "required"
    },
    {
      "stepType": "CreateDirective",
      "model": "TestSession",
      "field": "autoBaseline",
      "directive": "default"
    },
    {
      "stepType": "CreateDirectiveArgument",
      "model": "TestSession",
      "field": "autoBaseline",
      "directive": "default",
      "argument": "",
      "value": "false"
    },
    {
      "stepType": "CreateField",
      "model": "TestSession",
      "field": "baselineRef",
      "type": "Variation",
      "arity": "optional"
    },
    {
      "stepType": "CreateDirective",
      "model": "TestSession",
      "field": "baselineRef",
      "directive": "relation"
    },
    {
      "stepType": "CreateDirectiveArgument",
      "model": "TestSession",
      "field": "baselineRef",
      "directive": "relation",
      "argument": "name",
      "value": "\"VariationBaseline\""
    },
    {
      "stepType": "CreateField",
      "model": "TestSession",
      "field": "baselineForDiffRef",
      "type": "TestSession",
      "arity": "optional"
    },
    {
      "stepType": "CreateDirective",
      "model": "TestSession",
      "field": "baselineForDiffRef",
      "directive": "relation"
    },
    {
      "stepType": "CreateDirectiveArgument",
      "model": "TestSession",
      "field": "baselineForDiffRef",
      "directive": "relation",
      "argument": "name",
      "value": "\"DiffBaselineOnTestSession\""
    },
    {
      "stepType": "CreateField",
      "model": "TestSession",
      "field": "diffBaseline",
      "type": "TestSession",
      "arity": "optional"
    },
    {
      "stepType": "CreateDirective",
      "model": "TestSession",
      "field": "diffBaseline",
      "directive": "relation"
    },
    {
      "stepType": "CreateDirectiveArgument",
      "model": "TestSession",
      "field": "diffBaseline",
      "directive": "relation",
      "argument": "name",
      "value": "\"DiffBaselineOnTestSession\""
    }
  ]
}